usepolvo_core/__init__.py
usepolvo_core/auth/__init__.py
usepolvo_core/auth/api_key.py
usepolvo_core/auth/base.py
usepolvo_core/auth/basic.py
usepolvo_core/auth/bearer.py
usepolvo_core/auth/oauth2.py
usepolvo_core/core/__init__.py
usepolvo_core/core/client.py
usepolvo_core/core/exceptions.py
usepolvo_core/core/response.py
usepolvo_core/middleware/__init__.py
usepolvo_core/middleware/base.py
usepolvo_core/middleware/logging.py
usepolvo_core/middleware/rate_limit.py
usepolvo_core/middleware/retry.py
usepolvo_core/protocols/graphql/__init__.py
usepolvo_core/protocols/graphql/client.py
usepolvo_core/protocols/rest/__init__.py
usepolvo_core/protocols/rest/client.py
usepolvo_core/protocols/soap/__init__.py
usepolvo_core/protocols/soap/client.py
usepolvo_core/utils/__init__.py
usepolvo_core-0.1.0.dist-info/METADATA
usepolvo_core-0.1.0.dist-info/WHEEL
usepolvo_core-0.1.0.dist-info/top_level.txt
usepolvo_core-0.1.0.dist-info/RECORD
