Metadata-Version: 2.4
Name: usepolvo-core
Version: 0.1.0
Summary: A requests-style SDK for APIs
Author-email: Caio Pizzol <hi@usepolvo.com>
License-Expression: MIT
Requires-Python: >=3.8
Requires-Dist: httpx>=0.23.0
Provides-Extra: dev
Requires-Dist: black; extra == "dev"
Requires-Dist: isort; extra == "dev"
Requires-Dist: pre-commit; extra == "dev"
Requires-Dist: toml; extra == "dev"
Requires-Dist: pytest; extra == "dev"
Requires-Dist: pytest-cov; extra == "dev"
Requires-Dist: pytest-asyncio; extra == "dev"
Provides-Extra: all
Requires-Dist: usepolvo-core[dev]; extra == "all"
